pdd_sdk/__init__.py
pdd_sdk/api/__init__.py
pdd_sdk/api/base.py
pdd_sdk/api/rest/DdkGoodsDetail.py
pdd_sdk/api/rest/DdkGoodsPidGenerate.py
pdd_sdk/api/rest/DdkGoodsPidQuery.py
pdd_sdk/api/rest/DdkGoodsPromotionUrlGenerate.py
pdd_sdk/api/rest/DdkGoodsRecommendGet.py
pdd_sdk/api/rest/DdkGoodsSearch.py
pdd_sdk/api/rest/DdkGoodsZsUnitUrlGen.py
pdd_sdk/api/rest/DdkLotteryUrlGen.py
pdd_sdk/api/rest/DdkMallGoodsListGet.py
pdd_sdk/api/rest/DdkMallUrlGen.py
pdd_sdk/api/rest/DdkMerchantListGet.py
pdd_sdk/api/rest/DdkOrderDetailGet.py
pdd_sdk/api/rest/DdkOrderListIncrementGet.py
pdd_sdk/api/rest/DdkRpPromUrlGenerate.py
pdd_sdk/api/rest/DdkThemeGoodsSearch.py
pdd_sdk/api/rest/DdkThemeListGet.py
pdd_sdk/api/rest/DdkThemePromUrlGenerate.py
pdd_sdk/api/rest/DdkWeappQrcodeUrlGen.py
pdd_sdk/api/rest/GoodsCatsGet.py
pdd_sdk/api/rest/__init__.py
pdd_sdk-1.0.3.dist-info/LICENSE
pdd_sdk-1.0.3.dist-info/METADATA
pdd_sdk-1.0.3.dist-info/WHEEL
pdd_sdk-1.0.3.dist-info/top_level.txt
pdd_sdk-1.0.3.dist-info/RECORD
